pytronlinks/__init__.py
pytronlinks/client.py
pytronlinks-0.3.9.dist-info/DESCRIPTION.rst
pytronlinks-0.3.9.dist-info/METADATA
pytronlinks-0.3.9.dist-info/RECORD
pytronlinks-0.3.9.dist-info/WHEEL
pytronlinks-0.3.9.dist-info/metadata.json
pytronlinks-0.3.9.dist-info/top_level.txt
pytronlinks-0.3.9.dist-info/zip-safe
